dcm2niix-1.0.20250506.dist-info/RECORD
dcm2niix-1.0.20250506.dist-info/WHEEL
dcm2niix-1.0.20250506.dist-info/entry_points.txt
dcm2niix-1.0.20250506.dist-info/METADATA
dcm2niix-1.0.20250506.dist-info/licenses/license.txt
bin/dcm2niix
dcm2niix/_dist_ver.py
dcm2niix/__init__.py
dcm2niix/__main__.py
dcm2niix/dcm2niix
