Metadata-Version: 2.1
Name: dcm2niix
Version: 1.0.20250506
Summary: DCM2NIIX Python package
Keywords: research,jpeg,dicom,neuroscience,mri,neuroimaging,nifti,dcm,nii,nitrc,bids,dcm2niix,mricrogl
Author: Li X, Morgan PS, Ashburner J, Smith J, Rorden C
Maintainer-Email: Casper da Costa-Luis <imaging@cdcl.ml>
License: The following files are from different authors and have their own licenses
Classifier: Development Status :: 5 - Production/Stable
Classifier: Intended Audience :: Education
Classifier: Intended Audience :: Healthcare Industry
Classifier: Intended Audience :: Science/Research
Classifier: Operating System :: Microsoft :: Windows
Classifier: Operating System :: POSIX :: Linux
Classifier: Programming Language :: C++
Classifier: Programming Language :: Python :: 3
Classifier: Topic :: Scientific/Engineering :: Medical Science Apps.
Project-URL: Repository, https://github.com/rordenlab/dcm2niix
Project-URL: Changelog, https://github.com/rordenlab/dcm2niix/releases
Project-URL: Documentation, https://www.nitrc.org/plugins/mwiki/index.php/dcm2nii:MainPage
Requires-Python: >=3.7
